pytest_python_requests.py
pytest_requests-0.3.0.dist-info/LICENSE
pytest_requests-0.3.0.dist-info/METADATA
pytest_requests-0.3.0.dist-info/WHEEL
pytest_requests-0.3.0.dist-info/entry_points.txt
pytest_requests-0.3.0.dist-info/top_level.txt
pytest_requests-0.3.0.dist-info/RECORD
