Metadata-Version: 2.1
Name: pytest-requests
Version: 0.3.0
Summary: A simple plugin to use with pytest
Home-page: https://github.com/mariocesar/pytest-requests
Author: Mario Cesar Senoranis Ayala
Author-email: mariocesar@humanzilla.com
Maintainer: Mario Cesar Senoranis Ayala
Maintainer-email: mariocesar@humanzilla.com
License: MIT
Platform: UNKNOWN
Classifier: Development Status :: 4 - Beta
Classifier: Framework :: Pytest
Classifier: Intended Audience :: Developers
Classifier: Topic :: Software Development :: Testing
Classifier: Programming Language :: Python
Classifier: Programming Language :: Python :: 3
Classifier: Programming Language :: Python :: 3.6
Classifier: Programming Language :: Python :: 3.7
Classifier: Programming Language :: Python :: Implementation :: CPython
Classifier: Programming Language :: Python :: Implementation :: PyPy
Classifier: Operating System :: OS Independent
Classifier: License :: OSI Approved :: MIT License
Requires-Python: >=3.6
Requires-Dist: pytest (>=3.5.0)
Requires-Dist: pyyaml
Requires-Dist: pydash
Requires-Dist: trafaret
Requires-Dist: requests
